Metadata-Version: 1.1
Name: remove-cookies-notice
Version: 0.0.1
Summary: Tool to remove cookies notice in html pages
Home-page: https://github.com/owlint/CookiesNoticeRemover
Author: Laurent Evrard
Author-email: laurent@owlint.fr
License: WTFPL
Platform: UNKNOWN
Classifier: Programming Language :: Python
Classifier: Development Status :: 1 - Planning
Classifier: License :: OSI Approved
Classifier: Natural Language :: French
Classifier: Operating System :: OS Independent
Classifier: Programming Language :: Python :: 3.6
Classifier: Topic :: Communications
